yamlsql/__init__.py
yamlsql/core/__init__.py
yamlsql/core/crud_model.py
yamlsql/core/crud_router.py
yamlsql/core/schema_router.py
yamlsql/core/server.py
yamlsql/examples/__init__.py
yamlsql/examples/potato/__init__.py
yamlsql/examples/potato/__main__.py
yamlsql/examples/potato/app.py
yamlsql/examples/potato/potato.py
yamlsql/utils/__init__.py
yamlsql/utils/text.py
yamlsql-0.3.0.dist-info/LICENSE
yamlsql-0.3.0.dist-info/METADATA
yamlsql-0.3.0.dist-info/WHEEL
yamlsql-0.3.0.dist-info/top_level.txt
yamlsql-0.3.0.dist-info/RECORD
