Metadata-Version: 2.1
Name: yamlsql
Version: 0.3.0
Summary: Awesome yamlsql created by kristw
Home-page: https://github.com/kristw/yamlsql/
Author: kristw
License-File: LICENSE
Requires-Dist: fastapi
Requires-Dist: fastapi-crudrouter
Requires-Dist: sqlalchemy
Requires-Dist: pydantic <2
Provides-Extra: test
Requires-Dist: coverage ; extra == 'test'
Requires-Dist: gitchangelog ; extra == 'test'
Requires-Dist: isort ; extra == 'test'
Requires-Dist: mkdocs ; extra == 'test'
Requires-Dist: mypy ; extra == 'test'
Requires-Dist: pre-commit ; extra == 'test'
Requires-Dist: poetry ; extra == 'test'
Requires-Dist: pytest ; extra == 'test'
Requires-Dist: pytest-cov ; extra == 'test'
Requires-Dist: ruff ; extra == 'test'
Requires-Dist: uvicorn[standard] ; extra == 'test'
